README
naver_login.py
setup.py
Flask_naver.egg-info/PKG-INFO
Flask_naver.egg-info/SOURCES.txt
Flask_naver.egg-info/dependency_links.txt
Flask_naver.egg-info/not-zip-safe
Flask_naver.egg-info/requires.txt
Flask_naver.egg-info/top_level.txt