Metadata-Version: 1.1
Name: Flask-naver
Version: 1.2
Summary: Oauth2 wraper for Naver login
Home-page: http://github.com/seyriz/flask-naver
Author: Han-Wool, Lee
Author-email: kudnya@gmail.com
License: BSD
Platform: any
Classifier: Environment :: Web Environment
Classifier: Intended Audience :: Developers
Classifier: License :: OSI Approved :: BSD License
Classifier: Operating System :: OS Independent
Classifier: Programming Language :: Python
Classifier: Topic :: Internet :: WWW/HTTP :: Dynamic Content
Classifier: Topic :: Software Development :: Libraries :: Python Modules
